nonebot_plugin_emojimix/__init__.py
nonebot_plugin_emojimix/config.py
nonebot_plugin_emojimix/data_source.py
nonebot_plugin_emojimix/emoji_data.py
nonebot_plugin_emojimix-0.4.1.dist-info/LICENSE
nonebot_plugin_emojimix-0.4.1.dist-info/METADATA
nonebot_plugin_emojimix-0.4.1.dist-info/WHEEL
nonebot_plugin_emojimix-0.4.1.dist-info/RECORD
