Metadata-Version: 2.1
Name: nonebot_plugin_emojimix
Version: 0.4.1
Summary: Nonebot2 plugin for emojimix
Home-page: https://github.com/noneplugin/nonebot-plugin-emojimix
License: MIT
Author: meetwq
Author-email: meetwq@gmail.com
Requires-Python: >=3.9,<4.0
Classifier: License :: OSI Approved :: MIT License
Classifier: Programming Language :: Python :: 3
Classifier: Programming Language :: Python :: 3.9
Classifier: Programming Language :: Python :: 3.10
Classifier: Programming Language :: Python :: 3.11
Classifier: Programming Language :: Python :: 3.12
Classifier: Programming Language :: Python :: 3.13
Requires-Dist: emoji (>=2.0.0,<3.0.0)
Requires-Dist: httpx (>=0.26.0,<1.0.0)
Requires-Dist: nonebot-plugin-alconna (>=0.38.0,<1.0.0)
Requires-Dist: nonebot2 (>=2.3.0,<3.0.0)
Project-URL: Repository, https://github.com/noneplugin/nonebot-plugin-emojimix
